<annotation>
	<folder>images</folder>
	<filename>CAT_05_00001192_012.jpg</filename>
	<path>F:\New-forder\voc\train\images\CAT_05_00001192_012.jpg</path>
	<source>
		<database>Unknown</database>
	</source>
	<size>
		<width>452</width>
		<height>500</height>
		<depth>3</depth>
	</size>
	<segmented>0</segmented>
	<object>
		<name>cat</name>
		<pose>Unspecified</pose>
		<truncated>0</truncated>
		<difficult>0</difficult>
		<bndbox>
			<xmin>211</xmin>
			<ymin>55</ymin>
			<xmax>355</xmax>
			<ymax>231</ymax>
		</bndbox>
	</object>
</annotation>
